exifgps
