Metadata-Version: 1.0
Name: exifgps
Version: 1.014
Summary: EXIF GPS information to Google Maps url
Home-page: http://github.com/quincymd/exifgps
Author: Cambell Spong
Author-email: quincymd@mail.com
License: CC
Platform: UNKNOWN
